examples/MP_compliant_job.py
pymatgen/io/validation/__init__.py
pymatgen/io/validation/check_common_errors.py
pymatgen/io/validation/check_for_excess_empty_space.py
pymatgen/io/validation/check_incar.py
pymatgen/io/validation/check_kpoints_kspacing.py
pymatgen/io/validation/check_package_versions.py
pymatgen/io/validation/check_potcar.py
pymatgen/io/validation/common.py
pymatgen/io/validation/compare_to_MP_ehull.py
pymatgen/io/validation/py.typed
pymatgen/io/validation/settings.py
pymatgen/io/validation/validation.py
pymatgen/io/validation/vasp_defaults.py
pymatgen/io/validation/vasp_defaults.yaml
pymatgen_io_validation-0.1.1.dist-info/licenses/LICENSE
pymatgen_io_validation-0.1.1.dist-info/METADATA
pymatgen_io_validation-0.1.1.dist-info/WHEEL
pymatgen_io_validation-0.1.1.dist-info/top_level.txt
pymatgen_io_validation-0.1.1.dist-info/RECORD
