Metadata-Version: 2.4
Name: pymatgen-io-validation
Version: 0.1.1
Summary: A comprehensive I/O validator for electronic structure calculations
Home-page: https://github.com/materialsproject/pymatgen-io-validation
Author: Janosh Riebesell, Jason Munro, Aaron Kaplan
Author-email: Matthew Kuner <matthewkuner@gmail.com>
Maintainer: Matthew Kuner
License: modified BSD
Keywords: io,validation,dft,vasp
Classifier: Programming Language :: Python :: 3
Classifier: Programming Language :: Python :: 3.8
Classifier: Programming Language :: Python :: 3.9
Classifier: Programming Language :: Python :: 3.10
Classifier: Programming Language :: Python :: 3.11
Classifier: Development Status :: 4 - Beta
Classifier: Intended Audience :: Science/Research
Classifier: Operating System :: OS Independent
Classifier: Topic :: Scientific/Engineering
Classifier: Topic :: Scientific/Engineering :: Information Analysis
Classifier: Topic :: Scientific/Engineering :: Physics
Classifier: Topic :: Scientific/Engineering :: Chemistry
Classifier: Topic :: Software Development :: Libraries :: Python Modules
Requires-Python: >=3.8
License-File: LICENSE
Requires-Dist: pymatgen
Requires-Dist: numpy
Requires-Dist: requests
Requires-Dist: pydantic>=2.0.1
Requires-Dist: pydantic-settings>=2.0.0
Provides-Extra: dev
Requires-Dist: pre-commit>=2.12.1; extra == "dev"
Provides-Extra: tests
Requires-Dist: pytest==8.3.5; extra == "tests"
Requires-Dist: pytest-cov==6.1.1; extra == "tests"
Requires-Dist: types-requests; extra == "tests"
Dynamic: home-page
Dynamic: license-file
Dynamic: maintainer
